sirene/__init__.py
sirene/srn.py
sirene/srn_defl.py
sirene/srn_deprecated.py
sirene/MCTI/sexta_edicao/estim_6a_ed_1990-2020_agropecuaria.xlsx
sirene/MCTI/sexta_edicao/estim_6a_ed_1990-2020_energia.xlsx
sirene/MCTI/sexta_edicao/estim_6a_ed_1990-2020_ippu.xlsx
sirene/MCTI/sexta_edicao/estim_6a_ed_1990-2020_lulucf.xlsx
sirene/MCTI/sexta_edicao/estim_6a_ed_1990-2020_residuos.xlsx
sirene/MCTI/sexta_edicao/estim_6a_ed_1990-2020_total-brasil-1.xlsx
sirene/data/emissions_68_sectors_plus_hausehold_Gg_CO2e_GWP_SAR_v2.csv
sirene/data/public_data_scr_2012_12_a_2022_12_68TRU.csv
sirene/data/public_data_scr_and_sicor_2012_12_a_2022_12_68TRU.csv
sirene/data/public_data_scr_and_sicor_2012_to_2023_68TRU.csv
sirene/mapbiomas/coeficiente_desmatamento_por_bioma_atividade.csv
sirene-0.0.20.dist-info/LICENSE
sirene-0.0.20.dist-info/METADATA
sirene-0.0.20.dist-info/WHEEL
sirene-0.0.20.dist-info/top_level.txt
sirene-0.0.20.dist-info/RECORD
